src/__init__.py
src/main.py
SimpleWorkTime-0.2.0.dist-info/LICENSE
SimpleWorkTime-0.2.0.dist-info/METADATA
SimpleWorkTime-0.2.0.dist-info/WHEEL
SimpleWorkTime-0.2.0.dist-info/entry_points.txt
SimpleWorkTime-0.2.0.dist-info/top_level.txt
SimpleWorkTime-0.2.0.dist-info/RECORD
